tmplot/__init__.py
tmplot/_distance.py
tmplot/_helpers.py
tmplot/_metrics.py
tmplot/_report.py
tmplot/_stability.py
tmplot/_vis.py
tmplot-0.3.0.dist-info/licenses/LICENSE
tmplot-0.3.0.dist-info/METADATA
tmplot-0.3.0.dist-info/WHEEL
tmplot-0.3.0.dist-info/top_level.txt
tmplot-0.3.0.dist-info/RECORD
