Metadata-Version: 2.4
Name: tmplot
Version: 0.3.0
Summary: Visualization of Topic Modeling Results
Author-email: Maksim Terpilovskii <maximtrp@gmail.com>
License: MIT License
Project-URL: homepage, https://github.com/maximtrp/tmplot
Project-URL: documentation, https://tmplot.readthedocs.io/
Keywords: data science,data analytics
Classifier: License :: OSI Approved :: MIT License
Classifier: Operating System :: OS Independent
Classifier: Programming Language :: Python :: 3.8
Classifier: Programming Language :: Python :: 3.9
Classifier: Programming Language :: Python :: 3.10
Classifier: Programming Language :: Python :: 3.11
Classifier: Programming Language :: Python :: 3.12
Classifier: Topic :: Scientific/Engineering :: Information Analysis
Classifier: Topic :: Text Processing :: General
Requires-Python: >=3.8
License-File: LICENSE
Requires-Dist: numpy
Requires-Dist: seaborn
Requires-Dist: pandas
Requires-Dist: scikit-learn
Requires-Dist: scipy
Requires-Dist: altair
Requires-Dist: ipywidgets
Requires-Dist: tqdm
Provides-Extra: test
Requires-Dist: pytest; extra == "test"
Requires-Dist: coverage; extra == "test"
Provides-Extra: models
Requires-Dist: tomotopy>=0.8.0; extra == "models"
Requires-Dist: gensim; extra == "models"
Requires-Dist: bitermplus; extra == "models"
Dynamic: license-file
